main.py
setup.py
neursts.egg-info/PKG-INFO
neursts.egg-info/SOURCES.txt
neursts.egg-info/dependency_links.txt
neursts.egg-info/requires.txt
neursts.egg-info/top_level.txt